{
    "name": "气动扳手",
    "icon": "pneumaticcraft:pneumatic_wrench",
    "category": "pneumaticcraft:tools",
    "advancement": "pneumaticcraft:pressure_tube",
    "pages": [
        {
            "type": "text",
            "text": "气动扳手是 $thing扳手/$ 物品,适用于 $pncr.你可以用它执行多种任务,包括:$p$li$thing右键点击/$ 原版和模组方块以旋转它们$li$thing潜行+右键点击/$ $pncr 机器以将其作为物品掉落,保留任何存储的升级和机器内的空气."
        },
        {
            "type": "text",
            "text": "$li$thing右键点击/$ $l:base_concepts/drones无人机/$ 以拆解它们,使其作为物品掉落.$li$thing右键点击/$ $l:tubes/pressure_tubes压力管道/$ 以关闭/重新打开部分以隔离它们彼此.$p$item气动扳手/$ 必须在 $l:machines/charging_station充电站/$ 中加压后才能使用."
        },
        {
            "type": "crafting",
            "text": "制作气动扳手",
            "recipe": "pneumaticcraft:pneumatic_wrench"
        }
    ]
}